commit_parser/__init__.py
commit_parser/parser.py
sib_commit_parser-1.0.0.dist-info/METADATA
sib_commit_parser-1.0.0.dist-info/WHEEL
sib_commit_parser-1.0.0.dist-info/top_level.txt
sib_commit_parser-1.0.0.dist-info/RECORD
