Metadata-Version: 2.1
Name: sib-commit-parser
Version: 1.0.0
Summary: Commit parser for StartinBlox packages
License: MIT
Classifier: Programming Language :: Python :: 3
Classifier: Programming Language :: Python :: 3.5
Requires-Dist: python-semantic-release
Requires-Dist: ndebug
